grocropclient/TECH_DETAILS.md
grocropclient/__init__.py
grocropclient/constants.py
grocropclient/crop_budgets.py
grocropclient/crop_budgets_data.py
grocropclient/gro_crop_client.py
grocropclient-1.0.26.dist-info/LICENSE
grocropclient-1.0.26.dist-info/METADATA
grocropclient-1.0.26.dist-info/WHEEL
grocropclient-1.0.26.dist-info/RECORD
