Metadata-Version: 2.1
Name: grocropclient
Version: 1.0.26
Summary: Python client library for accessing Gro Intelligence's US crop insights
Home-page: https://www.gro-intelligence.com
License: MIT
Author: Gro Intelligence developers
Author-email: dev@gro-intelligence.com
Requires-Python: >=3.6.1,<4.0.0
Classifier: License :: OSI Approved :: MIT License
Classifier: Programming Language :: Python :: 3
Classifier: Programming Language :: Python :: 3.7
Classifier: Programming Language :: Python :: 3.8
Classifier: Programming Language :: Python :: 3.9
Classifier: Programming Language :: Python :: 3.10
Classifier: Programming Language :: Python :: 3.11
Requires-Dist: fuzzywuzzy
Requires-Dist: groclient
Requires-Dist: numpy
Requires-Dist: pandas
